.bzrignore
CHANGES.txt
LICENSE.GPL
LICENSE.txt
README.txt
bootstrap.py
buildout.cfg
setup.py
src/zw/__init__.py
src/zw.schema.egg-info/PKG-INFO
src/zw.schema.egg-info/SOURCES.txt
src/zw.schema.egg-info/dependency_links.txt
src/zw.schema.egg-info/namespace_packages.txt
src/zw.schema.egg-info/not-zip-safe
src/zw.schema.egg-info/requires.txt
src/zw.schema.egg-info/top_level.txt
src/zw/schema/__init__.py
src/zw/schema/i18n.py
src/zw/schema/color/README.txt
src/zw/schema/color/__init__.py
src/zw/schema/color/field.py
src/zw/schema/color/interfaces.py
src/zw/schema/color/tests.py