Metadata-Version: 1.0
Name: zw.schema
Version: 0.2.2
Summary: Additional schema fields for Zope 3
Home-page: https://launchpad.net/zw.schema
Author: Gregor Giesen
Author-email: giesen@zaehlwerk.net
License: GPLv3
Keywords: zope3
Platform: UNKNOWN
Classifier: Development Status :: 5 - Production/Stable
Classifier: Programming Language :: Python
Classifier: Environment :: Web Environment
Classifier: Topic :: Internet :: WWW/HTTP :: WSGI :: Application
Classifier: Framework :: Zope3
Classifier: Intended Audience :: Developers
Classifier: License :: OSI Approved :: GNU General Public License (GPL)
